playlistconverter/ApplePlaylist.py
playlistconverter/SpotifyCreator.py
playlistconverter/TrackInfo.py
playlistconverter-0.0.1.dist-info/LICENSE.txt
playlistconverter-0.0.1.dist-info/METADATA
playlistconverter-0.0.1.dist-info/WHEEL
playlistconverter-0.0.1.dist-info/top_level.txt
playlistconverter-0.0.1.dist-info/RECORD
