Metadata-Version: 2.1
Name: playlistconverter
Version: 0.0.1
Summary: Convert Apple Music to Spotify
Home-page: UNKNOWN
Author: Andrew King
Author-email: andrewking1597@gmail.com
License: UNKNOWN
Platform: UNKNOWN
License-File: LICENSE.txt
Requires-Dist: apple-music-python
Requires-Dist: certifi
Requires-Dist: cffi
Requires-Dist: chardet
Requires-Dist: cryptography
Requires-Dist: idna
Requires-Dist: pycparser
Requires-Dist: PyJWT
Requires-Dist: requests
Requires-Dist: six
Requires-Dist: spotipy
Requires-Dist: urllib3
